APIConnect/APIConnect.py
APIConnect/api_constants.py
APIConnect/api_utils.py
APIConnect/http.py
APIConnect/login_helper.py
APIConnect/order.py
APIConnect/order_helper.py
APIConnect/validator.py
apiconnect-2.0.10.data/data/conf/settings.ini
constants/action.py
constants/asset_type.py
constants/chart_exchange.py
constants/constants.py
constants/duration.py
constants/eod_Interval.py
constants/exchange.py
constants/intraday_interval.py
constants/order_type.py
constants/product_code.py
constants/results_stocks_news_category.py
constants/router.py
constants/segment_type.py
constants/streaming_constants.py
exceptions/api_exception.py
exceptions/validation_exception.py
feed/depth_feed.py
feed/feed.py
feed/livenews_feed.py
feed/miniQuote_feed.py
feed/orders_feed.py
feed/reduced_quotes_feed.py
feed/repeat_timer.py
resources/chart_response_formatter.py
resources/live_news_resource.py
resources/quote_resource.py
resources/watchlist_resource.py
services/live_news_service.py
services/quote_service.py
services/report_service.py
services/watchlist_service.py
apiconnect-2.0.10.dist-info/LICENSE.txt
apiconnect-2.0.10.dist-info/METADATA
apiconnect-2.0.10.dist-info/WHEEL
apiconnect-2.0.10.dist-info/top_level.txt
apiconnect-2.0.10.dist-info/RECORD
